MininetYingyongYuYuanmaPouxi/README.md
MininetYingyongYuYuanmaPouxi/__init__.py
MininetYingyongYuYuanmaPouxi/__main__.py
MininetYingyongYuYuanmaPouxi/file.epub
MininetYingyongYuYuanmaPouxi/index.html
MininetYingyongYuYuanmaPouxi/css/__init__.py
MininetYingyongYuYuanmaPouxi/css/annotations.css
MininetYingyongYuYuanmaPouxi/css/main.css
MininetYingyongYuYuanmaPouxi/css/normalize.css
MininetYingyongYuYuanmaPouxi/css/popup.css
MininetYingyongYuYuanmaPouxi/font/__init__.py
MininetYingyongYuYuanmaPouxi/font/fontello.eot
MininetYingyongYuYuanmaPouxi/font/fontello.svg
MininetYingyongYuYuanmaPouxi/font/fontello.ttf
MininetYingyongYuYuanmaPouxi/font/fontello.woff
MininetYingyongYuYuanmaPouxi/img/__init__.py
MininetYingyongYuYuanmaPouxi/img/annotator-glyph-sprite.png
MininetYingyongYuYuanmaPouxi/img/annotator-icon-sprite.png
MininetYingyongYuYuanmaPouxi/img/apple-touch-icon.png
MininetYingyongYuYuanmaPouxi/img/cancelfullscreen.png
MininetYingyongYuYuanmaPouxi/img/close.png
MininetYingyongYuYuanmaPouxi/img/fullscreen.png
MininetYingyongYuYuanmaPouxi/img/loader.gif
MininetYingyongYuYuanmaPouxi/img/menu-icon.png
MininetYingyongYuYuanmaPouxi/img/save.png
MininetYingyongYuYuanmaPouxi/img/saved.png
MininetYingyongYuYuanmaPouxi/img/settings-s.png
MininetYingyongYuYuanmaPouxi/img/settings.png
MininetYingyongYuYuanmaPouxi/img/star.png
MininetYingyongYuYuanmaPouxi/js/__init__.py
MininetYingyongYuYuanmaPouxi/js/epub.js
MininetYingyongYuYuanmaPouxi/js/epub.min.js
MininetYingyongYuYuanmaPouxi/js/epub.min.map
MininetYingyongYuYuanmaPouxi/js/hooks.min.js
MininetYingyongYuYuanmaPouxi/js/hooks.min.map
MininetYingyongYuYuanmaPouxi/js/reader.js
MininetYingyongYuYuanmaPouxi/js/reader.js.map
MininetYingyongYuYuanmaPouxi/js/reader.min.js
MininetYingyongYuYuanmaPouxi/js/reader.min.map
MininetYingyongYuYuanmaPouxi/js/hooks/__init__.py
MininetYingyongYuYuanmaPouxi/js/hooks/extensions/__init__.py
MininetYingyongYuYuanmaPouxi/js/hooks/extensions/highlight.js
mininet_yingyong_yu_yuanma_pouxi-2024.3.2.0.dist-info/METADATA
mininet_yingyong_yu_yuanma_pouxi-2024.3.2.0.dist-info/WHEEL
mininet_yingyong_yu_yuanma_pouxi-2024.3.2.0.dist-info/entry_points.txt
mininet_yingyong_yu_yuanma_pouxi-2024.3.2.0.dist-info/top_level.txt
mininet_yingyong_yu_yuanma_pouxi-2024.3.2.0.dist-info/RECORD
